manim_pptx/__init__.py
manim_pptx/pptxscene.py
manim_pptx/template.pptx
manim_pptx-0.1.6.dist-info/LICENSE
manim_pptx-0.1.6.dist-info/WHEEL
manim_pptx-0.1.6.dist-info/METADATA
manim_pptx-0.1.6.dist-info/RECORD
