Metadata-Version: 2.1
Name: manim-pptx
Version: 0.1.6
Summary: 
Author: RythenGlyth
Author-email: rythenglyth@gmail.com
Requires-Python: >=3.0,<4.0
Classifier: Programming Language :: Python :: 3
Classifier: Programming Language :: Python :: 3.10
Classifier: Programming Language :: Python :: 3.4
Classifier: Programming Language :: Python :: 3.5
Classifier: Programming Language :: Python :: 3.6
Classifier: Programming Language :: Python :: 3.7
Classifier: Programming Language :: Python :: 3.8
Classifier: Programming Language :: Python :: 3.9
Requires-Dist: lxml
Requires-Dist: manim
Requires-Dist: python-pptx
